{"variants":[{"traits":[{"interfaceLanguage":"swift"}],"paths":["\/documentation\/playdatekit\/playdate_sound\/init(channel:fileplayer:sample:sampleplayer:synth:sequence:effect:lfo:envelope:source:controlsignal:track:instrument:getcurrenttime:addsource:getdefaultchannel:addchannel:removechannel:setmiccallback:getheadphonestate:setoutputsactive:remov-1s8f3"]}],"sections":[],"schemaVersion":{"minor":3,"patch":0,"major":0},"metadata":{"modules":[{"name":"PlaydateKit"}],"roleHeading":"Initializer","fragments":[{"kind":"identifier","text":"init"},{"kind":"text","text":"("},{"text":"channel","kind":"externalParam"},{"text":": ","kind":"text"},{"text":"UnsafePointer","kind":"typeIdentifier","preciseIdentifier":"s:SP"},{"text":"<","kind":"text"},{"kind":"typeIdentifier","text":"playdate_sound_channel","preciseIdentifier":"c:@S@playdate_sound_channel"},{"text":">!, ","kind":"text"},{"text":"fileplayer","kind":"externalParam"},{"kind":"text","text":": "},{"kind":"typeIdentifier","preciseIdentifier":"s:SP","text":"UnsafePointer"},{"text":"<","kind":"text"},{"text":"playdate_sound_fileplayer","kind":"typeIdentifier","preciseIdentifier":"c:@S@playdate_sound_fileplayer"},{"kind":"text","text":">!, "},{"kind":"externalParam","text":"sample"},{"kind":"text","text":": "},{"text":"UnsafePointer","preciseIdentifier":"s:SP","kind":"typeIdentifier"},{"kind":"text","text":"<"},{"text":"playdate_sound_sample","preciseIdentifier":"c:@S@playdate_sound_sample","kind":"typeIdentifier"},{"text":">!, ","kind":"text"},{"kind":"externalParam","text":"sampleplayer"},{"kind":"text","text":": "},{"kind":"typeIdentifier","text":"UnsafePointer","preciseIdentifier":"s:SP"},{"text":"<","kind":"text"},{"preciseIdentifier":"c:@S@playdate_sound_sampleplayer","kind":"typeIdentifier","text":"playdate_sound_sampleplayer"},{"kind":"text","text":">!, "},{"kind":"externalParam","text":"synth"},{"text":": ","kind":"text"},{"text":"UnsafePointer","preciseIdentifier":"s:SP","kind":"typeIdentifier"},{"text":"<","kind":"text"},{"text":"playdate_sound_synth","kind":"typeIdentifier","preciseIdentifier":"c:@S@playdate_sound_synth"},{"kind":"text","text":">!, "},{"text":"sequence","kind":"externalParam"},{"text":": ","kind":"text"},{"text":"UnsafePointer","kind":"typeIdentifier","preciseIdentifier":"s:SP"},{"kind":"text","text":"<"},{"preciseIdentifier":"c:@S@playdate_sound_sequence","kind":"typeIdentifier","text":"playdate_sound_sequence"},{"text":">!, ","kind":"text"},{"text":"effect","kind":"externalParam"},{"text":": ","kind":"text"},{"kind":"typeIdentifier","text":"UnsafePointer","preciseIdentifier":"s:SP"},{"kind":"text","text":"<"},{"kind":"typeIdentifier","preciseIdentifier":"c:@S@playdate_sound_effect","text":"playdate_sound_effect"},{"text":">!, ","kind":"text"},{"kind":"externalParam","text":"lfo"},{"text":": ","kind":"text"},{"text":"UnsafePointer","preciseIdentifier":"s:SP","kind":"typeIdentifier"},{"text":"<","kind":"text"},{"text":"playdate_sound_lfo","preciseIdentifier":"c:@S@playdate_sound_lfo","kind":"typeIdentifier"},{"text":">!, ","kind":"text"},{"kind":"externalParam","text":"envelope"},{"kind":"text","text":": "},{"kind":"typeIdentifier","preciseIdentifier":"s:SP","text":"UnsafePointer"},{"text":"<","kind":"text"},{"preciseIdentifier":"c:@S@playdate_sound_envelope","text":"playdate_sound_envelope","kind":"typeIdentifier"},{"text":">!, ","kind":"text"},{"text":"source","kind":"externalParam"},{"text":": ","kind":"text"},{"kind":"typeIdentifier","text":"UnsafePointer","preciseIdentifier":"s:SP"},{"text":"<","kind":"text"},{"preciseIdentifier":"c:@S@playdate_sound_source","text":"playdate_sound_source","kind":"typeIdentifier"},{"kind":"text","text":">!, "},{"text":"controlsignal","kind":"externalParam"},{"text":": ","kind":"text"},{"text":"UnsafePointer","kind":"typeIdentifier","preciseIdentifier":"s:SP"},{"kind":"text","text":"<"},{"preciseIdentifier":"c:@S@playdate_control_signal","kind":"typeIdentifier","text":"playdate_control_signal"},{"text":">!, ","kind":"text"},{"text":"track","kind":"externalParam"},{"kind":"text","text":": "},{"preciseIdentifier":"s:SP","text":"UnsafePointer","kind":"typeIdentifier"},{"text":"<","kind":"text"},{"text":"playdate_sound_track","kind":"typeIdentifier","preciseIdentifier":"c:@S@playdate_sound_track"},{"text":">!, ","kind":"text"},{"kind":"externalParam","text":"instrument"},{"text":": ","kind":"text"},{"kind":"typeIdentifier","preciseIdentifier":"s:SP","text":"UnsafePointer"},{"text":"<","kind":"text"},{"preciseIdentifier":"c:@S@playdate_sound_instrument","text":"playdate_sound_instrument","kind":"typeIdentifier"},{"text":">!, ","kind":"text"},{"text":"getCurrentTime","kind":"externalParam"},{"kind":"text","text":": (() -> "},{"kind":"typeIdentifier","preciseIdentifier":"s:s6UInt32V","text":"UInt32"},{"text":")!, ","kind":"text"},{"kind":"externalParam","text":"addSource"},{"kind":"text","text":": (((("},{"kind":"typeIdentifier","text":"UnsafeMutableRawPointer","preciseIdentifier":"s:Sv"},{"text":"?, ","kind":"text"},{"kind":"typeIdentifier","text":"UnsafeMutablePointer","preciseIdentifier":"s:Sp"},{"text":"<","kind":"text"},{"kind":"typeIdentifier","preciseIdentifier":"s:s5Int16V","text":"Int16"},{"kind":"text","text":">?, "},{"preciseIdentifier":"s:Sp","kind":"typeIdentifier","text":"UnsafeMutablePointer"},{"text":"<","kind":"text"},{"preciseIdentifier":"s:s5Int16V","text":"Int16","kind":"typeIdentifier"},{"text":">?, ","kind":"text"},{"kind":"typeIdentifier","text":"Int32","preciseIdentifier":"s:s5Int32V"},{"text":") -> ","kind":"text"},{"kind":"typeIdentifier","preciseIdentifier":"s:s5Int32V","text":"Int32"},{"text":")?, ","kind":"text"},{"text":"UnsafeMutableRawPointer","preciseIdentifier":"s:Sv","kind":"typeIdentifier"},{"kind":"text","text":"?, "},{"kind":"typeIdentifier","preciseIdentifier":"s:s5Int32V","text":"Int32"},{"kind":"text","text":") -> "},{"kind":"typeIdentifier","preciseIdentifier":"s:s13OpaquePointerV","text":"OpaquePointer"},{"kind":"text","text":"?)!, "},{"kind":"externalParam","text":"getDefaultChannel"},{"text":": (() -> ","kind":"text"},{"text":"OpaquePointer","kind":"typeIdentifier","preciseIdentifier":"s:s13OpaquePointerV"},{"text":"?)!, ","kind":"text"},{"text":"addChannel","kind":"externalParam"},{"text":": ((","kind":"text"},{"preciseIdentifier":"s:s13OpaquePointerV","text":"OpaquePointer","kind":"typeIdentifier"},{"text":"?) -> ","kind":"text"},{"text":"Int32","preciseIdentifier":"s:s5Int32V","kind":"typeIdentifier"},{"kind":"text","text":")!, "},{"kind":"externalParam","text":"removeChannel"},{"kind":"text","text":": (("},{"kind":"typeIdentifier","text":"OpaquePointer","preciseIdentifier":"s:s13OpaquePointerV"},{"kind":"text","text":"?) -> "},{"kind":"typeIdentifier","preciseIdentifier":"s:s5Int32V","text":"Int32"},{"kind":"text","text":")!, "},{"text":"setMicCallback","kind":"externalParam"},{"text":": ((((","kind":"text"},{"kind":"typeIdentifier","text":"UnsafeMutableRawPointer","preciseIdentifier":"s:Sv"},{"kind":"text","text":"?, "},{"text":"UnsafeMutablePointer","kind":"typeIdentifier","preciseIdentifier":"s:Sp"},{"kind":"text","text":"<"},{"kind":"typeIdentifier","text":"Int16","preciseIdentifier":"s:s5Int16V"},{"text":">?, ","kind":"text"},{"preciseIdentifier":"s:s5Int32V","text":"Int32","kind":"typeIdentifier"},{"kind":"text","text":") -> "},{"kind":"typeIdentifier","preciseIdentifier":"s:s5Int32V","text":"Int32"},{"text":")?, ","kind":"text"},{"text":"UnsafeMutableRawPointer","kind":"typeIdentifier","preciseIdentifier":"s:Sv"},{"kind":"text","text":"?, "},{"kind":"typeIdentifier","preciseIdentifier":"c:@E@MicSource","text":"MicSource"},{"kind":"text","text":") -> "},{"text":"Int32","kind":"typeIdentifier","preciseIdentifier":"s:s5Int32V"},{"kind":"text","text":")!, "},{"text":"getHeadphoneState","kind":"externalParam"},{"kind":"text","text":": (("},{"preciseIdentifier":"s:Sp","kind":"typeIdentifier","text":"UnsafeMutablePointer"},{"kind":"text","text":"<"},{"preciseIdentifier":"s:s5Int32V","text":"Int32","kind":"typeIdentifier"},{"text":">?, ","kind":"text"},{"preciseIdentifier":"s:Sp","text":"UnsafeMutablePointer","kind":"typeIdentifier"},{"kind":"text","text":"<"},{"preciseIdentifier":"s:s5Int32V","kind":"typeIdentifier","text":"Int32"},{"kind":"text","text":">?, (("},{"text":"Int32","preciseIdentifier":"s:s5Int32V","kind":"typeIdentifier"},{"text":", ","kind":"text"},{"kind":"typeIdentifier","text":"Int32","preciseIdentifier":"s:s5Int32V"},{"kind":"text","text":") -> "},{"kind":"typeIdentifier","text":"Void","preciseIdentifier":"s:s4Voida"},{"kind":"text","text":")?) -> "},{"text":"Void","kind":"typeIdentifier","preciseIdentifier":"s:s4Voida"},{"kind":"text","text":")!, "},{"text":"setOutputsActive","kind":"externalParam"},{"kind":"text","text":": (("},{"text":"Int32","kind":"typeIdentifier","preciseIdentifier":"s:s5Int32V"},{"kind":"text","text":", "},{"text":"Int32","kind":"typeIdentifier","preciseIdentifier":"s:s5Int32V"},{"text":") -> ","kind":"text"},{"text":"Void","kind":"typeIdentifier","preciseIdentifier":"s:s4Voida"},{"kind":"text","text":")!, "},{"text":"removeSource","kind":"externalParam"},{"text":": ((","kind":"text"},{"preciseIdentifier":"s:s13OpaquePointerV","kind":"typeIdentifier","text":"OpaquePointer"},{"text":"?) -> ","kind":"text"},{"kind":"typeIdentifier","preciseIdentifier":"s:s5Int32V","text":"Int32"},{"kind":"text","text":")!, "},{"kind":"externalParam","text":"signal"},{"kind":"text","text":": "},{"kind":"typeIdentifier","text":"UnsafePointer","preciseIdentifier":"s:SP"},{"kind":"text","text":"<"},{"preciseIdentifier":"c:@S@playdate_sound_signal","text":"playdate_sound_signal","kind":"typeIdentifier"},{"kind":"text","text":">!, "},{"kind":"externalParam","text":"getError"},{"text":": (() -> ","kind":"text"},{"kind":"typeIdentifier","text":"UnsafePointer","preciseIdentifier":"s:SP"},{"kind":"text","text":"<"},{"preciseIdentifier":"s:s5CChara","text":"CChar","kind":"typeIdentifier"},{"text":">?)!)","kind":"text"}],"role":"symbol","symbolKind":"init","title":"init(channel:fileplayer:sample:sampleplayer:synth:sequence:effect:lfo:envelope:source:controlsignal:track:instrument:getCurrentTime:addSource:getDefaultChannel:addChannel:removeChannel:setMicCallback:getHeadphoneState:setOutputsActive:removeSource:signal:getError:)","externalID":"s:So14playdate_soundV7channel10fileplayer6sample12sampleplayer5synth8sequence6effect3lfo8envelope6source13controlsignal5track10instrument14getCurrentTime9addSource0P14DefaultChannel0sV006removeV014setMicCallback0P14HeadphoneState0X13OutputsActive0wT06signal0P5ErrorABSPySo0a1_b1_C0VGSg_SPySo0a1_b1_D0VGSgSPySo0a1_b1_E0VGSgSPySo0a1_b1_F0VGSgSPySo0a1_b1_G0VGSgSPySo0a1_b1_H0VGSgSPySo0a1_b1_I0VGSgSPySo0a1_b1_J0VGSgSPySo0a1_b1_K0VGSgSPySo0a1_b1_L0VGSgSPySo0A15_control_signalVGSgSPySo0a1_b1_N0VGSgSPySo0a1_b1_O0VGSgs6UInt32VyXCSgs13OpaquePointerVSgs5Int32VSvSg_Spys5Int16VGSgA63_A58_tXCSg_A59_A58_tXCSgA56_yXCSgA58_A56_XCSgA67_A58_A58_A59__A63_A58_tXCSg_A59_So0yT0VtXCSgySpyA58_GSg_A73_yA58__A58_tXCSgtXCSgA74_A67_SPySo0a1_B7_signalVGSgSPys4Int8VGSgyXCSgtcfc"},"primaryContentSections":[{"kind":"declarations","declarations":[{"tokens":[{"kind":"keyword","text":"init"},{"kind":"text","text":"("},{"text":"channel","kind":"externalParam"},{"text":": ","kind":"text"},{"kind":"typeIdentifier","preciseIdentifier":"s:SP","text":"UnsafePointer"},{"kind":"text","text":"<"},{"text":"playdate_sound_channel","identifier":"doc:\/\/PlaydateKit\/documentation\/PlaydateKit\/playdate_sound_channel","kind":"typeIdentifier","preciseIdentifier":"c:@S@playdate_sound_channel"},{"kind":"text","text":">!, "},{"text":"fileplayer","kind":"externalParam"},{"text":": ","kind":"text"},{"kind":"typeIdentifier","text":"UnsafePointer","preciseIdentifier":"s:SP"},{"text":"<","kind":"text"},{"kind":"typeIdentifier","preciseIdentifier":"c:@S@playdate_sound_fileplayer","identifier":"doc:\/\/PlaydateKit\/documentation\/PlaydateKit\/playdate_sound_fileplayer","text":"playdate_sound_fileplayer"},{"kind":"text","text":">!, "},{"kind":"externalParam","text":"sample"},{"text":": ","kind":"text"},{"text":"UnsafePointer","kind":"typeIdentifier","preciseIdentifier":"s:SP"},{"text":"<","kind":"text"},{"identifier":"doc:\/\/PlaydateKit\/documentation\/PlaydateKit\/playdate_sound_sample","preciseIdentifier":"c:@S@playdate_sound_sample","text":"playdate_sound_sample","kind":"typeIdentifier"},{"text":">!, ","kind":"text"},{"text":"sampleplayer","kind":"externalParam"},{"text":": ","kind":"text"},{"text":"UnsafePointer","kind":"typeIdentifier","preciseIdentifier":"s:SP"},{"text":"<","kind":"text"},{"text":"playdate_sound_sampleplayer","identifier":"doc:\/\/PlaydateKit\/documentation\/PlaydateKit\/playdate_sound_sampleplayer","kind":"typeIdentifier","preciseIdentifier":"c:@S@playdate_sound_sampleplayer"},{"kind":"text","text":">!, "},{"kind":"externalParam","text":"synth"},{"text":": ","kind":"text"},{"text":"UnsafePointer","kind":"typeIdentifier","preciseIdentifier":"s:SP"},{"text":"<","kind":"text"},{"identifier":"doc:\/\/PlaydateKit\/documentation\/PlaydateKit\/playdate_sound_synth","text":"playdate_sound_synth","kind":"typeIdentifier","preciseIdentifier":"c:@S@playdate_sound_synth"},{"text":">!, ","kind":"text"},{"text":"sequence","kind":"externalParam"},{"kind":"text","text":": "},{"preciseIdentifier":"s:SP","text":"UnsafePointer","kind":"typeIdentifier"},{"kind":"text","text":"<"},{"text":"playdate_sound_sequence","kind":"typeIdentifier","identifier":"doc:\/\/PlaydateKit\/documentation\/PlaydateKit\/playdate_sound_sequence","preciseIdentifier":"c:@S@playdate_sound_sequence"},{"text":">!, ","kind":"text"},{"kind":"externalParam","text":"effect"},{"kind":"text","text":": "},{"text":"UnsafePointer","kind":"typeIdentifier","preciseIdentifier":"s:SP"},{"text":"<","kind":"text"},{"identifier":"doc:\/\/PlaydateKit\/documentation\/PlaydateKit\/playdate_sound_effect","kind":"typeIdentifier","text":"playdate_sound_effect","preciseIdentifier":"c:@S@playdate_sound_effect"},{"kind":"text","text":">!, "},{"kind":"externalParam","text":"lfo"},{"kind":"text","text":": "},{"text":"UnsafePointer","preciseIdentifier":"s:SP","kind":"typeIdentifier"},{"text":"<","kind":"text"},{"text":"playdate_sound_lfo","kind":"typeIdentifier","preciseIdentifier":"c:@S@playdate_sound_lfo","identifier":"doc:\/\/PlaydateKit\/documentation\/PlaydateKit\/playdate_sound_lfo"},{"text":">!, ","kind":"text"},{"text":"envelope","kind":"externalParam"},{"text":": ","kind":"text"},{"kind":"typeIdentifier","text":"UnsafePointer","preciseIdentifier":"s:SP"},{"kind":"text","text":"<"},{"kind":"typeIdentifier","identifier":"doc:\/\/PlaydateKit\/documentation\/PlaydateKit\/playdate_sound_envelope","text":"playdate_sound_envelope","preciseIdentifier":"c:@S@playdate_sound_envelope"},{"kind":"text","text":">!, "},{"text":"source","kind":"externalParam"},{"kind":"text","text":": "},{"text":"UnsafePointer","kind":"typeIdentifier","preciseIdentifier":"s:SP"},{"text":"<","kind":"text"},{"text":"playdate_sound_source","preciseIdentifier":"c:@S@playdate_sound_source","identifier":"doc:\/\/PlaydateKit\/documentation\/PlaydateKit\/playdate_sound_source","kind":"typeIdentifier"},{"text":">!, ","kind":"text"},{"kind":"externalParam","text":"controlsignal"},{"kind":"text","text":": "},{"kind":"typeIdentifier","preciseIdentifier":"s:SP","text":"UnsafePointer"},{"text":"<","kind":"text"},{"text":"playdate_control_signal","preciseIdentifier":"c:@S@playdate_control_signal","identifier":"doc:\/\/PlaydateKit\/documentation\/PlaydateKit\/playdate_control_signal","kind":"typeIdentifier"},{"text":">!, ","kind":"text"},{"text":"track","kind":"externalParam"},{"kind":"text","text":": "},{"preciseIdentifier":"s:SP","text":"UnsafePointer","kind":"typeIdentifier"},{"kind":"text","text":"<"},{"kind":"typeIdentifier","identifier":"doc:\/\/PlaydateKit\/documentation\/PlaydateKit\/playdate_sound_track","text":"playdate_sound_track","preciseIdentifier":"c:@S@playdate_sound_track"},{"kind":"text","text":">!, "},{"kind":"externalParam","text":"instrument"},{"text":": ","kind":"text"},{"text":"UnsafePointer","preciseIdentifier":"s:SP","kind":"typeIdentifier"},{"kind":"text","text":"<"},{"identifier":"doc:\/\/PlaydateKit\/documentation\/PlaydateKit\/playdate_sound_instrument","text":"playdate_sound_instrument","kind":"typeIdentifier","preciseIdentifier":"c:@S@playdate_sound_instrument"},{"text":">!, ","kind":"text"},{"text":"getCurrentTime","kind":"externalParam"},{"text":": (() -> ","kind":"text"},{"preciseIdentifier":"s:s6UInt32V","text":"UInt32","kind":"typeIdentifier"},{"kind":"text","text":")!, "},{"kind":"externalParam","text":"addSource"},{"text":": ((((","kind":"text"},{"text":"UnsafeMutableRawPointer","kind":"typeIdentifier","preciseIdentifier":"s:Sv"},{"text":"?, ","kind":"text"},{"kind":"typeIdentifier","preciseIdentifier":"s:Sp","text":"UnsafeMutablePointer"},{"text":"<","kind":"text"},{"kind":"typeIdentifier","preciseIdentifier":"s:s5Int16V","text":"Int16"},{"kind":"text","text":">?, "},{"preciseIdentifier":"s:Sp","text":"UnsafeMutablePointer","kind":"typeIdentifier"},{"kind":"text","text":"<"},{"preciseIdentifier":"s:s5Int16V","kind":"typeIdentifier","text":"Int16"},{"text":">?, ","kind":"text"},{"text":"Int32","preciseIdentifier":"s:s5Int32V","kind":"typeIdentifier"},{"kind":"text","text":") -> "},{"kind":"typeIdentifier","preciseIdentifier":"s:s5Int32V","text":"Int32"},{"text":")?, ","kind":"text"},{"text":"UnsafeMutableRawPointer","kind":"typeIdentifier","preciseIdentifier":"s:Sv"},{"text":"?, ","kind":"text"},{"kind":"typeIdentifier","preciseIdentifier":"s:s5Int32V","text":"Int32"},{"kind":"text","text":") -> "},{"kind":"typeIdentifier","preciseIdentifier":"s:s13OpaquePointerV","text":"OpaquePointer"},{"text":"?)!, ","kind":"text"},{"text":"getDefaultChannel","kind":"externalParam"},{"kind":"text","text":": (() -> "},{"kind":"typeIdentifier","preciseIdentifier":"s:s13OpaquePointerV","text":"OpaquePointer"},{"text":"?)!, ","kind":"text"},{"kind":"externalParam","text":"addChannel"},{"text":": ((","kind":"text"},{"preciseIdentifier":"s:s13OpaquePointerV","kind":"typeIdentifier","text":"OpaquePointer"},{"text":"?) -> ","kind":"text"},{"kind":"typeIdentifier","text":"Int32","preciseIdentifier":"s:s5Int32V"},{"kind":"text","text":")!, "},{"kind":"externalParam","text":"removeChannel"},{"text":": ((","kind":"text"},{"text":"OpaquePointer","kind":"typeIdentifier","preciseIdentifier":"s:s13OpaquePointerV"},{"text":"?) -> ","kind":"text"},{"preciseIdentifier":"s:s5Int32V","text":"Int32","kind":"typeIdentifier"},{"text":")!, ","kind":"text"},{"kind":"externalParam","text":"setMicCallback"},{"text":": ((((","kind":"text"},{"preciseIdentifier":"s:Sv","text":"UnsafeMutableRawPointer","kind":"typeIdentifier"},{"text":"?, ","kind":"text"},{"text":"UnsafeMutablePointer","preciseIdentifier":"s:Sp","kind":"typeIdentifier"},{"text":"<","kind":"text"},{"preciseIdentifier":"s:s5Int16V","text":"Int16","kind":"typeIdentifier"},{"text":">?, ","kind":"text"},{"preciseIdentifier":"s:s5Int32V","kind":"typeIdentifier","text":"Int32"},{"kind":"text","text":") -> "},{"kind":"typeIdentifier","text":"Int32","preciseIdentifier":"s:s5Int32V"},{"kind":"text","text":")?, "},{"text":"UnsafeMutableRawPointer","kind":"typeIdentifier","preciseIdentifier":"s:Sv"},{"text":"?, ","kind":"text"},{"text":"MicSource","preciseIdentifier":"c:@E@MicSource","identifier":"doc:\/\/PlaydateKit\/documentation\/PlaydateKit\/MicSource","kind":"typeIdentifier"},{"text":") -> ","kind":"text"},{"kind":"typeIdentifier","preciseIdentifier":"s:s5Int32V","text":"Int32"},{"kind":"text","text":")!, "},{"kind":"externalParam","text":"getHeadphoneState"},{"kind":"text","text":": (("},{"kind":"typeIdentifier","text":"UnsafeMutablePointer","preciseIdentifier":"s:Sp"},{"kind":"text","text":"<"},{"text":"Int32","preciseIdentifier":"s:s5Int32V","kind":"typeIdentifier"},{"kind":"text","text":">?, "},{"kind":"typeIdentifier","preciseIdentifier":"s:Sp","text":"UnsafeMutablePointer"},{"kind":"text","text":"<"},{"preciseIdentifier":"s:s5Int32V","text":"Int32","kind":"typeIdentifier"},{"text":">?, ((","kind":"text"},{"text":"Int32","kind":"typeIdentifier","preciseIdentifier":"s:s5Int32V"},{"text":", ","kind":"text"},{"kind":"typeIdentifier","preciseIdentifier":"s:s5Int32V","text":"Int32"},{"kind":"text","text":") -> "},{"text":"Void","preciseIdentifier":"s:s4Voida","kind":"typeIdentifier"},{"text":")?) -> ","kind":"text"},{"preciseIdentifier":"s:s4Voida","text":"Void","kind":"typeIdentifier"},{"kind":"text","text":")!, "},{"text":"setOutputsActive","kind":"externalParam"},{"text":": ((","kind":"text"},{"kind":"typeIdentifier","text":"Int32","preciseIdentifier":"s:s5Int32V"},{"kind":"text","text":", "},{"kind":"typeIdentifier","preciseIdentifier":"s:s5Int32V","text":"Int32"},{"kind":"text","text":") -> "},{"text":"Void","preciseIdentifier":"s:s4Voida","kind":"typeIdentifier"},{"text":")!, ","kind":"text"},{"kind":"externalParam","text":"removeSource"},{"kind":"text","text":": (("},{"preciseIdentifier":"s:s13OpaquePointerV","text":"OpaquePointer","kind":"typeIdentifier"},{"text":"?) -> ","kind":"text"},{"preciseIdentifier":"s:s5Int32V","text":"Int32","kind":"typeIdentifier"},{"text":")!, ","kind":"text"},{"kind":"externalParam","text":"signal"},{"text":": ","kind":"text"},{"kind":"typeIdentifier","text":"UnsafePointer","preciseIdentifier":"s:SP"},{"text":"<","kind":"text"},{"kind":"typeIdentifier","text":"playdate_sound_signal","identifier":"doc:\/\/PlaydateKit\/documentation\/PlaydateKit\/playdate_sound_signal","preciseIdentifier":"c:@S@playdate_sound_signal"},{"kind":"text","text":">!, "},{"text":"getError","kind":"externalParam"},{"text":": (() -> ","kind":"text"},{"text":"UnsafePointer","kind":"typeIdentifier","preciseIdentifier":"s:SP"},{"text":"<","kind":"text"},{"kind":"typeIdentifier","preciseIdentifier":"s:s5CChara","text":"CChar"},{"text":">?)!)","kind":"text"}],"languages":["swift"],"platforms":["macOS"]}]}],"identifier":{"url":"doc:\/\/PlaydateKit\/documentation\/PlaydateKit\/playdate_sound\/init(channel:fileplayer:sample:sampleplayer:synth:sequence:effect:lfo:envelope:source:controlsignal:track:instrument:getCurrentTime:addSource:getDefaultChannel:addChannel:removeChannel:setMicCallback:getHeadphoneState:setOutputsActive:removeSource:signal:getError:)","interfaceLanguage":"swift"},"hierarchy":{"paths":[["doc:\/\/PlaydateKit\/documentation\/PlaydateKit","doc:\/\/PlaydateKit\/documentation\/PlaydateKit\/playdate_sound"]]},"kind":"symbol","references":{"doc://PlaydateKit/documentation/PlaydateKit/MicSource":{"fragments":[{"text":"enum","kind":"keyword"},{"kind":"text","text":" "},{"text":"MicSource","kind":"identifier"}],"role":"symbol","kind":"symbol","title":"MicSource","abstract":[],"type":"topic","url":"\/documentation\/playdatekit\/micsource","identifier":"doc:\/\/PlaydateKit\/documentation\/PlaydateKit\/MicSource","navigatorTitle":[{"text":"MicSource","kind":"identifier"}]},"doc://PlaydateKit/documentation/PlaydateKit/playdate_sound":{"url":"\/documentation\/playdatekit\/playdate_sound","title":"playdate_sound","type":"topic","identifier":"doc:\/\/PlaydateKit\/documentation\/PlaydateKit\/playdate_sound","fragments":[{"kind":"keyword","text":"struct"},{"kind":"text","text":" "},{"text":"playdate_sound","kind":"identifier"}],"abstract":[],"kind":"symbol","navigatorTitle":[{"kind":"identifier","text":"playdate_sound"}],"role":"symbol"},"doc://PlaydateKit/documentation/PlaydateKit/playdate_sound_source":{"role":"symbol","abstract":[],"type":"topic","identifier":"doc:\/\/PlaydateKit\/documentation\/PlaydateKit\/playdate_sound_source","title":"playdate_sound_source","url":"\/documentation\/playdatekit\/playdate_sound_source","fragments":[{"kind":"keyword","text":"struct"},{"kind":"text","text":" "},{"text":"playdate_sound_source","kind":"identifier"}],"navigatorTitle":[{"text":"playdate_sound_source","kind":"identifier"}],"kind":"symbol"},"doc://PlaydateKit/documentation/PlaydateKit/playdate_sound_effect":{"role":"symbol","type":"topic","kind":"symbol","url":"\/documentation\/playdatekit\/playdate_sound_effect","abstract":[],"identifier":"doc:\/\/PlaydateKit\/documentation\/PlaydateKit\/playdate_sound_effect","navigatorTitle":[{"kind":"identifier","text":"playdate_sound_effect"}],"title":"playdate_sound_effect","fragments":[{"kind":"keyword","text":"struct"},{"text":" ","kind":"text"},{"text":"playdate_sound_effect","kind":"identifier"}]},"doc://PlaydateKit/documentation/PlaydateKit/playdate_control_signal":{"type":"topic","kind":"symbol","abstract":[],"url":"\/documentation\/playdatekit\/playdate_control_signal","title":"playdate_control_signal","role":"symbol","identifier":"doc:\/\/PlaydateKit\/documentation\/PlaydateKit\/playdate_control_signal","fragments":[{"kind":"keyword","text":"struct"},{"text":" ","kind":"text"},{"kind":"identifier","text":"playdate_control_signal"}],"navigatorTitle":[{"text":"playdate_control_signal","kind":"identifier"}]},"doc://PlaydateKit/documentation/PlaydateKit":{"url":"\/documentation\/playdatekit","type":"topic","title":"PlaydateKit","identifier":"doc:\/\/PlaydateKit\/documentation\/PlaydateKit","abstract":[{"type":"text","text":"Create games for Playdate using Swift."}],"kind":"symbol","images":[{"type":"icon","identifier":"Logo.png"}],"role":"collection"},"doc://PlaydateKit/documentation/PlaydateKit/playdate_sound_signal":{"title":"playdate_sound_signal","kind":"symbol","url":"\/documentation\/playdatekit\/playdate_sound_signal","fragments":[{"kind":"keyword","text":"struct"},{"text":" ","kind":"text"},{"text":"playdate_sound_signal","kind":"identifier"}],"navigatorTitle":[{"kind":"identifier","text":"playdate_sound_signal"}],"abstract":[],"role":"symbol","type":"topic","identifier":"doc:\/\/PlaydateKit\/documentation\/PlaydateKit\/playdate_sound_signal"},"doc://PlaydateKit/documentation/PlaydateKit/playdate_sound_sampleplayer":{"identifier":"doc:\/\/PlaydateKit\/documentation\/PlaydateKit\/playdate_sound_sampleplayer","kind":"symbol","title":"playdate_sound_sampleplayer","abstract":[],"url":"\/documentation\/playdatekit\/playdate_sound_sampleplayer","role":"symbol","fragments":[{"text":"struct","kind":"keyword"},{"kind":"text","text":" "},{"kind":"identifier","text":"playdate_sound_sampleplayer"}],"type":"topic","navigatorTitle":[{"kind":"identifier","text":"playdate_sound_sampleplayer"}]},"doc://PlaydateKit/documentation/PlaydateKit/playdate_sound_channel":{"fragments":[{"text":"struct","kind":"keyword"},{"text":" ","kind":"text"},{"kind":"identifier","text":"playdate_sound_channel"}],"url":"\/documentation\/playdatekit\/playdate_sound_channel","abstract":[],"role":"symbol","identifier":"doc:\/\/PlaydateKit\/documentation\/PlaydateKit\/playdate_sound_channel","kind":"symbol","navigatorTitle":[{"kind":"identifier","text":"playdate_sound_channel"}],"type":"topic","title":"playdate_sound_channel"},"doc://PlaydateKit/documentation/PlaydateKit/playdate_sound_instrument":{"kind":"symbol","abstract":[],"role":"symbol","navigatorTitle":[{"kind":"identifier","text":"playdate_sound_instrument"}],"fragments":[{"text":"struct","kind":"keyword"},{"kind":"text","text":" "},{"kind":"identifier","text":"playdate_sound_instrument"}],"url":"\/documentation\/playdatekit\/playdate_sound_instrument","type":"topic","identifier":"doc:\/\/PlaydateKit\/documentation\/PlaydateKit\/playdate_sound_instrument","title":"playdate_sound_instrument"},"doc://PlaydateKit/documentation/PlaydateKit/playdate_sound_synth":{"role":"symbol","identifier":"doc:\/\/PlaydateKit\/documentation\/PlaydateKit\/playdate_sound_synth","abstract":[],"url":"\/documentation\/playdatekit\/playdate_sound_synth","type":"topic","fragments":[{"text":"struct","kind":"keyword"},{"kind":"text","text":" "},{"text":"playdate_sound_synth","kind":"identifier"}],"title":"playdate_sound_synth","navigatorTitle":[{"text":"playdate_sound_synth","kind":"identifier"}],"kind":"symbol"},"doc://PlaydateKit/documentation/PlaydateKit/playdate_sound_track":{"kind":"symbol","abstract":[],"role":"symbol","navigatorTitle":[{"text":"playdate_sound_track","kind":"identifier"}],"identifier":"doc:\/\/PlaydateKit\/documentation\/PlaydateKit\/playdate_sound_track","url":"\/documentation\/playdatekit\/playdate_sound_track","fragments":[{"kind":"keyword","text":"struct"},{"kind":"text","text":" "},{"text":"playdate_sound_track","kind":"identifier"}],"title":"playdate_sound_track","type":"topic"},"doc://PlaydateKit/documentation/PlaydateKit/playdate_sound/init(channel:fileplayer:sample:sampleplayer:synth:sequence:effect:lfo:envelope:source:controlsignal:track:instrument:getCurrentTime:addSource:getDefaultChannel:addChannel:removeChannel:setMicCallback:getHeadphoneState:setOutputsActive:removeSource:signal:getError:)":{"title":"init(channel:fileplayer:sample:sampleplayer:synth:sequence:effect:lfo:envelope:source:controlsignal:track:instrument:getCurrentTime:addSource:getDefaultChannel:addChannel:removeChannel:setMicCallback:getHeadphoneState:setOutputsActive:removeSource:signal:getError:)","abstract":[],"identifier":"doc:\/\/PlaydateKit\/documentation\/PlaydateKit\/playdate_sound\/init(channel:fileplayer:sample:sampleplayer:synth:sequence:effect:lfo:envelope:source:controlsignal:track:instrument:getCurrentTime:addSource:getDefaultChannel:addChannel:removeChannel:setMicCallback:getHeadphoneState:setOutputsActive:removeSource:signal:getError:)","role":"symbol","fragments":[{"text":"init","kind":"identifier"},{"kind":"text","text":"("},{"kind":"externalParam","text":"channel"},{"text":": ","kind":"text"},{"kind":"typeIdentifier","preciseIdentifier":"s:SP","text":"UnsafePointer"},{"kind":"text","text":"<"},{"text":"playdate_sound_channel","kind":"typeIdentifier","preciseIdentifier":"c:@S@playdate_sound_channel"},{"kind":"text","text":">!, "},{"text":"fileplayer","kind":"externalParam"},{"text":": ","kind":"text"},{"kind":"typeIdentifier","preciseIdentifier":"s:SP","text":"UnsafePointer"},{"text":"<","kind":"text"},{"preciseIdentifier":"c:@S@playdate_sound_fileplayer","text":"playdate_sound_fileplayer","kind":"typeIdentifier"},{"kind":"text","text":">!, "},{"kind":"externalParam","text":"sample"},{"kind":"text","text":": "},{"preciseIdentifier":"s:SP","kind":"typeIdentifier","text":"UnsafePointer"},{"text":"<","kind":"text"},{"text":"playdate_sound_sample","preciseIdentifier":"c:@S@playdate_sound_sample","kind":"typeIdentifier"},{"kind":"text","text":">!, "},{"kind":"externalParam","text":"sampleplayer"},{"text":": ","kind":"text"},{"text":"UnsafePointer","kind":"typeIdentifier","preciseIdentifier":"s:SP"},{"kind":"text","text":"<"},{"kind":"typeIdentifier","preciseIdentifier":"c:@S@playdate_sound_sampleplayer","text":"playdate_sound_sampleplayer"},{"kind":"text","text":">!, "},{"kind":"externalParam","text":"synth"},{"kind":"text","text":": "},{"text":"UnsafePointer","preciseIdentifier":"s:SP","kind":"typeIdentifier"},{"text":"<","kind":"text"},{"text":"playdate_sound_synth","preciseIdentifier":"c:@S@playdate_sound_synth","kind":"typeIdentifier"},{"kind":"text","text":">!, "},{"kind":"externalParam","text":"sequence"},{"text":": ","kind":"text"},{"text":"UnsafePointer","preciseIdentifier":"s:SP","kind":"typeIdentifier"},{"kind":"text","text":"<"},{"preciseIdentifier":"c:@S@playdate_sound_sequence","kind":"typeIdentifier","text":"playdate_sound_sequence"},{"text":">!, ","kind":"text"},{"kind":"externalParam","text":"effect"},{"text":": ","kind":"text"},{"text":"UnsafePointer","preciseIdentifier":"s:SP","kind":"typeIdentifier"},{"kind":"text","text":"<"},{"kind":"typeIdentifier","text":"playdate_sound_effect","preciseIdentifier":"c:@S@playdate_sound_effect"},{"text":">!, ","kind":"text"},{"text":"lfo","kind":"externalParam"},{"kind":"text","text":": "},{"kind":"typeIdentifier","preciseIdentifier":"s:SP","text":"UnsafePointer"},{"text":"<","kind":"text"},{"preciseIdentifier":"c:@S@playdate_sound_lfo","text":"playdate_sound_lfo","kind":"typeIdentifier"},{"text":">!, ","kind":"text"},{"kind":"externalParam","text":"envelope"},{"kind":"text","text":": "},{"text":"UnsafePointer","kind":"typeIdentifier","preciseIdentifier":"s:SP"},{"kind":"text","text":"<"},{"preciseIdentifier":"c:@S@playdate_sound_envelope","text":"playdate_sound_envelope","kind":"typeIdentifier"},{"text":">!, ","kind":"text"},{"text":"source","kind":"externalParam"},{"text":": ","kind":"text"},{"kind":"typeIdentifier","preciseIdentifier":"s:SP","text":"UnsafePointer"},{"text":"<","kind":"text"},{"preciseIdentifier":"c:@S@playdate_sound_source","kind":"typeIdentifier","text":"playdate_sound_source"},{"kind":"text","text":">!, "},{"kind":"externalParam","text":"controlsignal"},{"kind":"text","text":": "},{"text":"UnsafePointer","kind":"typeIdentifier","preciseIdentifier":"s:SP"},{"kind":"text","text":"<"},{"text":"playdate_control_signal","kind":"typeIdentifier","preciseIdentifier":"c:@S@playdate_control_signal"},{"text":">!, ","kind":"text"},{"kind":"externalParam","text":"track"},{"text":": ","kind":"text"},{"text":"UnsafePointer","preciseIdentifier":"s:SP","kind":"typeIdentifier"},{"text":"<","kind":"text"},{"kind":"typeIdentifier","preciseIdentifier":"c:@S@playdate_sound_track","text":"playdate_sound_track"},{"text":">!, ","kind":"text"},{"text":"instrument","kind":"externalParam"},{"kind":"text","text":": "},{"kind":"typeIdentifier","preciseIdentifier":"s:SP","text":"UnsafePointer"},{"text":"<","kind":"text"},{"text":"playdate_sound_instrument","kind":"typeIdentifier","preciseIdentifier":"c:@S@playdate_sound_instrument"},{"text":">!, ","kind":"text"},{"text":"getCurrentTime","kind":"externalParam"},{"kind":"text","text":": (() -> "},{"preciseIdentifier":"s:s6UInt32V","text":"UInt32","kind":"typeIdentifier"},{"kind":"text","text":")!, "},{"text":"addSource","kind":"externalParam"},{"kind":"text","text":": (((("},{"preciseIdentifier":"s:Sv","text":"UnsafeMutableRawPointer","kind":"typeIdentifier"},{"text":"?, ","kind":"text"},{"text":"UnsafeMutablePointer","preciseIdentifier":"s:Sp","kind":"typeIdentifier"},{"kind":"text","text":"<"},{"kind":"typeIdentifier","preciseIdentifier":"s:s5Int16V","text":"Int16"},{"kind":"text","text":">?, "},{"kind":"typeIdentifier","preciseIdentifier":"s:Sp","text":"UnsafeMutablePointer"},{"kind":"text","text":"<"},{"preciseIdentifier":"s:s5Int16V","text":"Int16","kind":"typeIdentifier"},{"text":">?, ","kind":"text"},{"text":"Int32","kind":"typeIdentifier","preciseIdentifier":"s:s5Int32V"},{"text":") -> ","kind":"text"},{"preciseIdentifier":"s:s5Int32V","kind":"typeIdentifier","text":"Int32"},{"kind":"text","text":")?, "},{"kind":"typeIdentifier","preciseIdentifier":"s:Sv","text":"UnsafeMutableRawPointer"},{"kind":"text","text":"?, "},{"preciseIdentifier":"s:s5Int32V","kind":"typeIdentifier","text":"Int32"},{"kind":"text","text":") -> "},{"text":"OpaquePointer","preciseIdentifier":"s:s13OpaquePointerV","kind":"typeIdentifier"},{"text":"?)!, ","kind":"text"},{"text":"getDefaultChannel","kind":"externalParam"},{"kind":"text","text":": (() -> "},{"kind":"typeIdentifier","text":"OpaquePointer","preciseIdentifier":"s:s13OpaquePointerV"},{"text":"?)!, ","kind":"text"},{"kind":"externalParam","text":"addChannel"},{"kind":"text","text":": (("},{"kind":"typeIdentifier","text":"OpaquePointer","preciseIdentifier":"s:s13OpaquePointerV"},{"text":"?) -> ","kind":"text"},{"text":"Int32","kind":"typeIdentifier","preciseIdentifier":"s:s5Int32V"},{"kind":"text","text":")!, "},{"text":"removeChannel","kind":"externalParam"},{"kind":"text","text":": (("},{"kind":"typeIdentifier","preciseIdentifier":"s:s13OpaquePointerV","text":"OpaquePointer"},{"text":"?) -> ","kind":"text"},{"text":"Int32","kind":"typeIdentifier","preciseIdentifier":"s:s5Int32V"},{"text":")!, ","kind":"text"},{"kind":"externalParam","text":"setMicCallback"},{"kind":"text","text":": (((("},{"kind":"typeIdentifier","text":"UnsafeMutableRawPointer","preciseIdentifier":"s:Sv"},{"kind":"text","text":"?, "},{"kind":"typeIdentifier","text":"UnsafeMutablePointer","preciseIdentifier":"s:Sp"},{"kind":"text","text":"<"},{"text":"Int16","kind":"typeIdentifier","preciseIdentifier":"s:s5Int16V"},{"kind":"text","text":">?, "},{"text":"Int32","kind":"typeIdentifier","preciseIdentifier":"s:s5Int32V"},{"text":") -> ","kind":"text"},{"kind":"typeIdentifier","text":"Int32","preciseIdentifier":"s:s5Int32V"},{"kind":"text","text":")?, "},{"kind":"typeIdentifier","preciseIdentifier":"s:Sv","text":"UnsafeMutableRawPointer"},{"text":"?, ","kind":"text"},{"text":"MicSource","kind":"typeIdentifier","preciseIdentifier":"c:@E@MicSource"},{"text":") -> ","kind":"text"},{"preciseIdentifier":"s:s5Int32V","kind":"typeIdentifier","text":"Int32"},{"text":")!, ","kind":"text"},{"kind":"externalParam","text":"getHeadphoneState"},{"kind":"text","text":": (("},{"preciseIdentifier":"s:Sp","text":"UnsafeMutablePointer","kind":"typeIdentifier"},{"kind":"text","text":"<"},{"text":"Int32","kind":"typeIdentifier","preciseIdentifier":"s:s5Int32V"},{"kind":"text","text":">?, "},{"kind":"typeIdentifier","text":"UnsafeMutablePointer","preciseIdentifier":"s:Sp"},{"text":"<","kind":"text"},{"kind":"typeIdentifier","text":"Int32","preciseIdentifier":"s:s5Int32V"},{"text":">?, ((","kind":"text"},{"text":"Int32","kind":"typeIdentifier","preciseIdentifier":"s:s5Int32V"},{"kind":"text","text":", "},{"preciseIdentifier":"s:s5Int32V","kind":"typeIdentifier","text":"Int32"},{"kind":"text","text":") -> "},{"preciseIdentifier":"s:s4Voida","text":"Void","kind":"typeIdentifier"},{"kind":"text","text":")?) -> "},{"text":"Void","kind":"typeIdentifier","preciseIdentifier":"s:s4Voida"},{"text":")!, ","kind":"text"},{"kind":"externalParam","text":"setOutputsActive"},{"kind":"text","text":": (("},{"kind":"typeIdentifier","preciseIdentifier":"s:s5Int32V","text":"Int32"},{"text":", ","kind":"text"},{"text":"Int32","kind":"typeIdentifier","preciseIdentifier":"s:s5Int32V"},{"text":") -> ","kind":"text"},{"kind":"typeIdentifier","text":"Void","preciseIdentifier":"s:s4Voida"},{"kind":"text","text":")!, "},{"kind":"externalParam","text":"removeSource"},{"kind":"text","text":": (("},{"text":"OpaquePointer","kind":"typeIdentifier","preciseIdentifier":"s:s13OpaquePointerV"},{"text":"?) -> ","kind":"text"},{"text":"Int32","kind":"typeIdentifier","preciseIdentifier":"s:s5Int32V"},{"text":")!, ","kind":"text"},{"kind":"externalParam","text":"signal"},{"text":": ","kind":"text"},{"text":"UnsafePointer","kind":"typeIdentifier","preciseIdentifier":"s:SP"},{"kind":"text","text":"<"},{"kind":"typeIdentifier","preciseIdentifier":"c:@S@playdate_sound_signal","text":"playdate_sound_signal"},{"kind":"text","text":">!, "},{"text":"getError","kind":"externalParam"},{"text":": (() -> ","kind":"text"},{"kind":"typeIdentifier","preciseIdentifier":"s:SP","text":"UnsafePointer"},{"kind":"text","text":"<"},{"preciseIdentifier":"s:s5CChara","kind":"typeIdentifier","text":"CChar"},{"kind":"text","text":">?)!)"}],"kind":"symbol","url":"\/documentation\/playdatekit\/playdate_sound\/init(channel:fileplayer:sample:sampleplayer:synth:sequence:effect:lfo:envelope:source:controlsignal:track:instrument:getcurrenttime:addsource:getdefaultchannel:addchannel:removechannel:setmiccallback:getheadphonestate:setoutputsactive:remov-1s8f3","type":"topic"},"Logo.png":{"alt":null,"variants":[{"url":"\/images\/PlaydateKit\/Logo.png","traits":["1x","light"]}],"type":"image","identifier":"Logo.png"},"doc://PlaydateKit/documentation/PlaydateKit/playdate_sound_fileplayer":{"kind":"symbol","title":"playdate_sound_fileplayer","navigatorTitle":[{"text":"playdate_sound_fileplayer","kind":"identifier"}],"fragments":[{"kind":"keyword","text":"struct"},{"text":" ","kind":"text"},{"text":"playdate_sound_fileplayer","kind":"identifier"}],"abstract":[],"url":"\/documentation\/playdatekit\/playdate_sound_fileplayer","role":"symbol","identifier":"doc:\/\/PlaydateKit\/documentation\/PlaydateKit\/playdate_sound_fileplayer","type":"topic"},"doc://PlaydateKit/documentation/PlaydateKit/playdate_sound_envelope":{"navigatorTitle":[{"text":"playdate_sound_envelope","kind":"identifier"}],"role":"symbol","abstract":[],"type":"topic","identifier":"doc:\/\/PlaydateKit\/documentation\/PlaydateKit\/playdate_sound_envelope","fragments":[{"text":"struct","kind":"keyword"},{"kind":"text","text":" "},{"kind":"identifier","text":"playdate_sound_envelope"}],"url":"\/documentation\/playdatekit\/playdate_sound_envelope","kind":"symbol","title":"playdate_sound_envelope"},"doc://PlaydateKit/documentation/PlaydateKit/playdate_sound_sequence":{"url":"\/documentation\/playdatekit\/playdate_sound_sequence","identifier":"doc:\/\/PlaydateKit\/documentation\/PlaydateKit\/playdate_sound_sequence","role":"symbol","title":"playdate_sound_sequence","fragments":[{"kind":"keyword","text":"struct"},{"text":" ","kind":"text"},{"kind":"identifier","text":"playdate_sound_sequence"}],"abstract":[],"type":"topic","kind":"symbol","navigatorTitle":[{"text":"playdate_sound_sequence","kind":"identifier"}]},"doc://PlaydateKit/documentation/PlaydateKit/playdate_sound_sample":{"title":"playdate_sound_sample","fragments":[{"kind":"keyword","text":"struct"},{"kind":"text","text":" "},{"kind":"identifier","text":"playdate_sound_sample"}],"type":"topic","identifier":"doc:\/\/PlaydateKit\/documentation\/PlaydateKit\/playdate_sound_sample","kind":"symbol","url":"\/documentation\/playdatekit\/playdate_sound_sample","abstract":[],"navigatorTitle":[{"kind":"identifier","text":"playdate_sound_sample"}],"role":"symbol"},"doc://PlaydateKit/documentation/PlaydateKit/playdate_sound_lfo":{"role":"symbol","type":"topic","abstract":[],"identifier":"doc:\/\/PlaydateKit\/documentation\/PlaydateKit\/playdate_sound_lfo","title":"playdate_sound_lfo","url":"\/documentation\/playdatekit\/playdate_sound_lfo","fragments":[{"kind":"keyword","text":"struct"},{"text":" ","kind":"text"},{"text":"playdate_sound_lfo","kind":"identifier"}],"navigatorTitle":[{"text":"playdate_sound_lfo","kind":"identifier"}],"kind":"symbol"}}}